{
    "scalingModes": [
        {
            "name": "Anime4K",
            "effects": [
                {
                    "name": "Anime4K\\Anime4K_Restore_Soft_VL"
                },
                {
                    "name": "Bilinear",
                    "scalingType": 3
                }
            ]
        },
        {
            "name": "Anime4K + 3D AA",
            "effects": [
                {
                    "name": "Anime4K\\Anime4K_Restore_Soft_VL"
                },
                {
                    "name": "Anime4K\\Anime4K_3D_AA_Upscale_US"
                },
                {
                    "name": "Bilinear",
                    "scalingType": 3
                }
            ]
        },
        {
            "name": "Anime4K + CRT",
            "effects": [
                {
                    "name": "Anime4K\\Anime4K_Restore_Soft_VL"
                },
                {
                    "name": "CRT\\CRT_Lottes",
                    "scalingType": 3
                }
            ]
        }
    ]
}